[
  {
    "title": "HTML",
    "imageSrc": "skills/html.png"
  },
  {
    "title": "CSS",
    "imageSrc": "skills/css.png"
  },
  {
    "title": "React",
    "imageSrc": "skills/react.png"
  },
  {
    "title": "Docker",
    "imageSrc": "skills/docker.png"
  },
  {
    "title": "Python",
    "imageSrc": "skills/python.png"
  },
  {
    "title": "PostgresDB",
    "imageSrc": "skills/postgres.png"
  },
  {
    "title": "Linux",
    "imageSrc": "skills/linux.png"
  },
  {
    "title": "Azure",
    "imageSrc": "skills/azure.png"
  },
  {
    "title": "C#",
    "imageSrc": "skills/c_sharp.png"
  },
  {
    "title": "Elixir",
    "imageSrc": "skills/elixir.png"
  },
  {
    "title": "Figma",
    "imageSrc": "skills/figma.png"
  }
]
